{
  "id": "education",
  "en": {
    "title": "education",
    "data": [
      {
        "title": "bachelor",
        "location": "waterloo, on",
        "name": "university of waterloo",
        "startYear": "2015",
        "endYear": "2020",
        "description": [
          "bachelor of applied science, with distinction.",
          "major: computer engineering, honours.",
          "president's scholarship.",
          "mississauga chapter of professional engineers ontario (peo) scholarship.",
          "should have gone to cs but at least i have this cheap ass ring.",
          "did not have a convocation or grad trip due to corona :(("
        ]
      },
      {
        "title": "highschool",
        "location": "mississauga, on",
        "name": "st. joan of arc catholic secondary school",
        "startYear": "2011",
        "endYear": "2015",
        "description": [
          "honour roll, computer engineering, computer science, transportation technology, and academic business awards.",
          "ict shsm.",
          "100+ hours of volunteer work.",
          "nobody here was religious.",
          "where i discovered alcohol."
        ]
      },
      {
        "title": "koreanschool",
        "location": "mississauga, on",
        "name": "rick hansen secondary school (korean school)",
        "startYear": "2003",
        "endYear": "2015",
        "description": [
          "wanted to die every saturday morning.",
          "was supposed to learn korean but only learned kpop instead."
        ]
      }
    ],
    "img": {
      "alt": "education.png",
      "src": "../assets/education.png"
    }
  },
  "kr": {
    "title": "교육",
    "data": [
      {
        "title": "bachelor",
        "location": "워털루, 온타리오",
        "name": "워털루 대학교",
        "startYear": "2015",
        "endYear": "2020",
        "description": [
          "bachelor of applied science, with distinction 수상.",
          "전공: 컴퓨터 공학, 명예.",
          "president's scholarship 수상.",
          "mississauga chapter of professional engineers ontario (peo) 협회 장학금 수상.",
          "컴사에 갔어야하지만 적어도이 작은 엔지니어 반지가 있습니다.",
          "코로나로 인해 졸업식 또는 졸업여행이 없었습니다 :(("
        ]
      },
      {
        "title": "highschool",
        "location": "mississauga, 온타리오",
        "name": "st. joan of arc 카톨릭 고등학교",
        "startYear": "2011",
        "endYear": "2015",
        "description": [
          "honour roll, computer engineering, computer science, transportation technology, and academic business awards 수상.",
          "ict shsm.",
          "100 시간 이상의 봉사 활동.",
          "여기 아무도 종교적이지 않았습니다.",
          "내가 술을 발견 한 곳."
        ]
      },
      {
        "title": "koreanschool",
        "location": "mississauga, 온타리오",
        "name": "릭 한센 중 고등 학교 (한글 학교)",
        "startYear": "2003",
        "endYear": "2015",
        "description": [
          "매주 토요일 아침에 나는 죽고 싶었다.",
          "한국어를 배워야했지만 kpop만 배웠습니다."
        ]
      }
    ],
    "img": {
      "alt": "education.png",
      "src": "../assets/education.png"
    }
  }
}
